{
"type": "FeatureCollection",
"name": "ZHU labels",
"crs": { "type": "name", "properties": { "name": "urn:ogc:def:crs:OGC:1.3:CRS84" } },
"features": [
{ "type": "Feature", "properties": { "filters": [ 23 ], "bcg": 23, "size": 1, "text": null, "layer": null, "path": null, "underline": false, "opaque": false, "xOffset": -50, "yOffset": 2, "isTextDefaults": true }, "geometry": { "type": "Point", "coordinates": [ 180.0, 90.0 ] } },
{ "type": "Feature", "properties": { "filters": [ ], "bcg": null, "size": null, "text": [ "72 SFC-ABV" ], "layer": null, "path": null, "underline": false, "opaque": false, "xOffset": null, "yOffset": null, "isTextDefaults": false }, "geometry": { "type": "Point", "coordinates": [ -88.387467483225564, 27.023453653964474 ] } },
{ "type": "Feature", "properties": { "filters": [ ], "bcg": null, "size": null, "text": [ "24 110-340" ], "layer": null, "path": null, "underline": false, "opaque": false, "xOffset": null, "yOffset": null, "isTextDefaults": false }, "geometry": { "type": "Point", "coordinates": [ -89.087726053387357, 29.391975288335246 ] } },
{ "type": "Feature", "properties": { "filters": [ ], "bcg": null, "size": null, "text": [ "92 350-ABV" ], "layer": null, "path": null, "underline": false, "opaque": false, "xOffset": null, "yOffset": null, "isTextDefaults": false }, "geometry": { "type": "Point", "coordinates": [ -89.087726053387357, 28.907973041311653 ] } },
{ "type": "Feature", "properties": { "filters": [ ], "bcg": null, "size": null, "text": [ "63 240-340" ], "layer": null, "path": null, "underline": false, "opaque": false, "xOffset": null, "yOffset": null, "isTextDefaults": false }, "geometry": { "type": "Point", "coordinates": [ -88.789086369053635, 31.240451955159394 ] } },
{ "type": "Feature", "properties": { "filters": [ ], "bcg": null, "size": null, "text": [ "37 350-ABV" ], "layer": null, "path": null, "underline": false, "opaque": false, "xOffset": null, "yOffset": null, "isTextDefaults": false }, "geometry": { "type": "Point", "coordinates": [ -88.763341568680033, 30.843982029406025 ] } },
{ "type": "Feature", "properties": { "filters": [ ], "bcg": null, "size": null, "text": [ "25 SFC-230" ], "layer": null, "path": null, "underline": false, "opaque": false, "xOffset": null, "yOffset": null, "isTextDefaults": false }, "geometry": { "type": "Point", "coordinates": [ -88.753043648530564, 30.470682423988897 ] } }
]
}
